MANIFEST.in
README.rst
setup.py
bodleian/__init__.py
bodleian.recipe.fedora.egg-info/PKG-INFO
bodleian.recipe.fedora.egg-info/SOURCES.txt
bodleian.recipe.fedora.egg-info/dependency_links.txt
bodleian.recipe.fedora.egg-info/entry_points.txt
bodleian.recipe.fedora.egg-info/namespace_packages.txt
bodleian.recipe.fedora.egg-info/not-zip-safe
bodleian.recipe.fedora.egg-info/requires.txt
bodleian.recipe.fedora.egg-info/top_level.txt
bodleian/recipe/__init__.py
bodleian/recipe/fedora/__init__.py
bodleian/recipe/fedora/recipe_config.ini
bodleian/recipe/fedora/version.txt