Metadata-Version: 1.1
Name: bodleian.recipe.fedora
Version: 1.0.2
Summary: zc.buildout to configure a fedora instance
Home-page: http://pypi.python.org/pypi/bodleian.recipe.fedora
Author: CB
Author-email: github@bodleian.ox.ac.uk
License: MIT
Platform: UNKNOWN
Classifier: Framework :: Buildout
Classifier: Intended Audience :: Developers
Classifier: License :: OSI Approved :: MIT License
Classifier: Topic :: Software Development :: Build Tools
